dsntnn/__init__.py
dsntnn-0.5.3.dist-info/LICENSE
dsntnn-0.5.3.dist-info/METADATA
dsntnn-0.5.3.dist-info/WHEEL
dsntnn-0.5.3.dist-info/top_level.txt
dsntnn-0.5.3.dist-info/RECORD
