Metadata-Version: 2.1
Name: dsntnn
Version: 0.5.3
Summary: PyTorch implementation of DSNT
Home-page: UNKNOWN
Author: Aiden Nibali
License: Apache Software License 2.0
Platform: UNKNOWN
Classifier: Intended Audience :: Developers
Classifier: License :: OSI Approved :: Apache Software License
Classifier: Topic :: Software Development :: Libraries
Classifier: Programming Language :: Python
Classifier: Programming Language :: Python :: 3
Requires-Dist: torch (>=0.4)
